Workbook

Sheet README
A1: OpenFinanceKit — MVP v0.1.0
A2: Sistema de gestión financiera personal
A4: ¿Qué es OpenFinanceKit?
A5: OpenFinanceKit es un sistema para administrar finanzas personales.
A6: Permite registrar ingresos, gastos y pagos, calcular el estado financiero
A7: del mes y visualizar un resumen general en el Dashboard.
A9: Hojas del libro
A10: Hoja | B10: Descripción
A11: README | B11: Este archivo. Descripción y guía de uso.
A12: LOG | B12: Historial de cambios del libro.
A13: Configuración | B13: Categorías, cuentas y parámetros. No modificar sin criterio.
A14: Ingresos | B14: Registra todos tus ingresos. Solo datos, sin fórmulas.
A15: Gastos | B15: Registra todos tus gastos. Solo datos, sin fórmulas.
A16: Pagos | B16: Pagos programados y su estado (Pendiente/Pagado/Vencido).
A17: Motor | B17: Realiza TODOS los cálculos. No editar directamente.
A18: Dashboard | B18: Resumen visual. Solo lectura.
A20: Reglas de uso
A21: RN-001 Configuración es la única fuente de datos maestros.
A22: RN-002 Motor es la única hoja autorizada para realizar cálculos.
A23: RN-003 Dashboard únicamente visualiza información.
A24: RN-004 Las hojas de captura (Ingresos, Gastos, Pagos) solo almacenan datos.
A25: RN-005 Las listas desplegables obtienen sus valores desde Configuración.
A26: RN-006 Las tablas permiten agregar filas sin modificar fórmulas.

Sheet LOG
A1: LOG — Historial de cambios
A3: Versión | B3: Fecha | C3: Sprint | D3: Autor | E3: Descripción
A4: v0.1.0 | B4: 2026-08-03 | C4: Sprint 1 | D4: Gustavo Echeverría | E4: Creación del MVP — 8 hojas, 6 tablas, Motor y Dashboard

Sheet Configuración
A1: Configuración — Datos maestros del sistema
A2: tblCategorias | E2: tblCuentas
A3: CategoriaID | B3: Nombre | C3: Tipo | E3: CuentaID | F3: Nombre | G3: SaldoInicial
A4: 1 | B4: Sueldo | C4: Ingreso | E4: 1 | F4: Efectivo | G4: 0
A5: 2 | B5: Freelance | C5: Ingreso | E5: 2 | F5: Banco | G5: 0
A6: 3 | B6: Otros ingresos | C6: Ingreso | E6: 3 | F6: Tarjeta | G6: 0
A7: 4 | B7: Alimentación | C7: Gasto
A8: 5 | B8: Transporte | C8: Gasto
A10: tblParametros
A11: Parametro | B11: Valor
A12: MesActual | B12: 2026-08
A13: Moneda | B13: USD
A14: Version | B14: 0.1.0

Sheet Ingresos
A1: Ingresos — Registro de ingresos
A2: tblIngresos — Solo datos. No agregar fórmulas en esta hoja.
A3: ID | B3: Fecha | C3: Categoria | D3: Cuenta | E3: Valor | F3: Descripcion
A4: 1 | B4: 2026-08-01 | C4: Sueldo | D4: Banco | E4: 3500 | F4: Sueldo agosto
A5: 2 | B5: 2026-08-05 | C5: Freelance | D5: Efectivo | E5: 500 | F5: Proyecto web

Sheet Gastos
A1: Gastos — Registro de gastos
A2: tblGastos — Solo datos. No agregar fórmulas en esta hoja.
A3: ID | B3: Fecha | C3: Categoria | D3: Cuenta | E3: Valor | F3: Descripcion
A4: 1 | B4: 2026-08-02 | C4: Alimentación | D4: Efectivo | E4: 120 | F4: Supermercado
A5: 2 | B5: 2026-08-03 | C5: Transporte | D5: Efectivo | E5: 45 | F5: Gasolina

Sheet Pagos
A1: Pagos — Pagos programados
A2: tblPagos — Solo datos. No agregar fórmulas en esta hoja.
A3: ID | B3: Concepto | C3: FechaVencimiento | D3: Valor | E3: Estado
A4: 1 | B4: Internet | C4: 2026-08-10 | D4: 45 | E4: Pendiente
A5: 2 | B5: Seguro | C5: 2026-08-15 | D5: 120 | E5: Pendiente
A6: 3 | B6: Gimnasio | C6: 2026-07-30 | D6: 35 | E6: Vencido

Sheet Motor
A1: Motor — Centro de cálculos
A2: ⚠️ Esta hoja realiza TODOS los cálculos. No editar directamente.
A4: Resumen del mes | D4: Ingresos por categoría
A5: Total Ingresos del mes | B5: =SUMPRODUCT((TEXT(tblIngresos[Fecha],"YYYY-MM")=INDEX(tblParametros[Valor],MATCH("MesActual",tblParametros[Parametro],0)))*tblIngresos[Valor]) | D5: Sueldo | E5: =SUMIF(tblIngresos[Categoria],"Sueldo",tblIngresos[Valor])
A6: Total Gastos del mes | B6: =SUMPRODUCT((TEXT(tblGastos[Fecha],"YYYY-MM")=INDEX(tblParametros[Valor],MATCH("MesActual",tblParametros[Parametro],0)))*tblGastos[Valor]) | D6: Freelance | E6: =SUMIF(tblIngresos[Categoria],"Freelance",tblIngresos[Valor])
A7: Balance del mes | B7: =B5-B6 | D7: Otros ingresos | E7: =SUMIF(tblIngresos[Categoria],"Otros ingresos",tblIngresos[Valor])
A9: Saldos por cuenta | D9: Gastos por categoría
A10: Saldo — Efectivo | B10: =SUMIF(tblCuentas[Nombre],"Efectivo",tblCuentas[SaldoInicial])+SUMIF(tblIngresos[Cuenta],"Efectivo",tblIngresos[Valor])-SUMIF(tblGastos[Cuenta],"Efectivo",tblGastos[Valor]) | D10: Alimentación | E10: =SUMIF(tblGastos[Categoria],"Alimentación",tblGastos[Valor])
A11: Saldo — Banco | B11: =SUMIF(tblCuentas[Nombre],"Banco",tblCuentas[SaldoInicial])+SUMIF(tblIngresos[Cuenta],"Banco",tblIngresos[Valor])-SUMIF(tblGastos[Cuenta],"Banco",tblGastos[Valor]) | D11: Transporte | E11: =SUMIF(tblGastos[Categoria],"Transporte",tblGastos[Valor])
A12: Saldo — Tarjeta | B12: =SUMIF(tblCuentas[Nombre],"Tarjeta",tblCuentas[SaldoInicial])+SUMIF(tblIngresos[Cuenta],"Tarjeta",tblIngresos[Valor])-SUMIF(tblGastos[Cuenta],"Tarjeta",tblGastos[Valor])
A14: Totales generales
A15: Total Ingresos (histórico) | B15: =SUM(tblIngresos[Valor])
A16: Total Gastos (histórico) | B16: =SUM(tblGastos[Valor])
A17: Saldo actual total | B17: =SUM(tblCuentas[SaldoInicial])+B15-B16
A19: Pagos
A20: Pendiente de pago | B20: =SUMIF(tblPagos[Estado],"Pendiente",tblPagos[Valor])
A21: Total vencido | B21: =SUMIF(tblPagos[Estado],"Vencido",tblPagos[Valor])
A22: Total pagado | B22: =SUMIF(tblPagos[Estado],"Pagado",tblPagos[Valor])

Sheet Dashboard
A1: OpenFinanceKit — Dashboard
A2: =CONCATENATE("Período: ",IFERROR(INDEX(tblParametros[Valor],MATCH("MesActual",tblParametros[Parametro],0)),"N/A"))
A4: 💰 INGRESOS | B4: 💸 GASTOS | C4: 📊 BALANCE | D4: ⏳ PENDIENTE | E4: 🚨 VENCIDO
A5: =Motor!B5 | B5: =Motor!B6 | C5: =Motor!B7 | D5: =Motor!B20 | E5: =Motor!B21
A7: Saldos por cuenta
A8: Cuenta | B8: Saldo Inicial | C8: Entradas | D8: Salidas | E8: Saldo Actual
A9: Efectivo | B9: =SUMIF(tblCuentas[Nombre],"Efectivo",tblCuentas[SaldoInicial]) | C9: =SUMIF(tblIngresos[Cuenta],"Efectivo",tblIngresos[Valor]) | D9: =SUMIF(tblGastos[Cuenta],"Efectivo",tblGastos[Valor]) | E9: =Motor!B10
A10: Banco | B10: =SUMIF(tblCuentas[Nombre],"Banco",tblCuentas[SaldoInicial]) | C10: =SUMIF(tblIngresos[Cuenta],"Banco",tblIngresos[Valor]) | D10: =SUMIF(tblGastos[Cuenta],"Banco",tblGastos[Valor]) | E10: =Motor!B11
A11: Tarjeta | B11: =SUMIF(tblCuentas[Nombre],"Tarjeta",tblCuentas[SaldoInicial]) | C11: =SUMIF(tblIngresos[Cuenta],"Tarjeta",tblIngresos[Valor]) | D11: =SUMIF(tblGastos[Cuenta],"Tarjeta",tblGastos[Valor]) | E11: =Motor!B12
A13: Resumen del mes
A14: Total Ingresos del mes | B14: =Motor!B5
A15: Total Gastos del mes | B15: =Motor!B6
A16: Balance del mes | B16: =Motor!B7
A17: Pendiente de pago | B17: =Motor!B20
A18: Total vencido | B18: =Motor!B21
A21: ⚠️ Solo lectura. No editar. Los datos provienen del Motor.
